pi7447/__init__.py
pi7447/pi7447.py
pi7447-1.0.1.dist-info/LICENSE
pi7447-1.0.1.dist-info/METADATA
pi7447-1.0.1.dist-info/WHEEL
pi7447-1.0.1.dist-info/top_level.txt
pi7447-1.0.1.dist-info/RECORD
