Metadata-Version: 2.1
Name: pi7447
Version: 1.0.1
Summary: 7447 lib for raspberry pi
Home-page: https://github.com/p208p2002/pi7447
Author: Philip Huang
Author-email: p208p2002@gmail.com
License: UNKNOWN
Platform: UNKNOWN
Classifier: Programming Language :: Python :: 3
Classifier: License :: OSI Approved :: MIT License
Classifier: Operating System :: OS Independent
